nsequence/__init__.py
nsequence/exceptions.py
nsequence/nsequence.py
nsequence-0.1.8.dist-info/LICENSE.md
nsequence-0.1.8.dist-info/METADATA
nsequence-0.1.8.dist-info/WHEEL
nsequence-0.1.8.dist-info/top_level.txt
nsequence-0.1.8.dist-info/RECORD
