Metadata-Version: 2.1
Name: nsequence
Version: 0.1.8
Summary: A Library for Manipulating Progressions or Sequences
Author-email: Isaac Houngue <isaac.houngue@imsp-uac.org>
License: Copyright 2024, Isaac Houngue
Project-URL: homepage, https://github.com/wehappit/nsequence
Project-URL: documentation, https://github.com/wehappit/nsequence
Project-URL: repository, https://github.com/wehappit/nsequence
Project-URL: changelog, https://github.com/wehappit/nsequence/blob/main/CHANGELOG.md
Keywords: progression,arithmetic progression,sequence,fonctional sequence,progression terms computation
Classifier: License :: OSI Approved :: Apache Software License
Classifier: Topic :: Utilities
Classifier: Topic :: Software Development :: Libraries
Classifier: Programming Language :: Python
Classifier: Programming Language :: Python :: 3
Requires-Python: >=3.6
License-File: LICENSE.md
Provides-Extra: build
Requires-Dist: build ; extra == 'build'
Requires-Dist: twine ; extra == 'build'
Provides-Extra: dev
Requires-Dist: black ; extra == 'dev'
Requires-Dist: bumpver ; extra == 'dev'
Requires-Dist: pytest ; extra == 'dev'
Requires-Dist: pytest-cov ; extra == 'dev'
